sigdis/__about__.py
sigdis/__init__.py
sigdis-1.0.1.dist-info/METADATA
sigdis-1.0.1.dist-info/WHEEL
sigdis-1.0.1.dist-info/licenses/LICENSE.txt
sigdis-1.0.1.dist-info/RECORD
