Metadata-Version: 2.1
Name: sigdis
Version: 1.0.1
Summary: Signal dispatcher
Project-URL: Documentation, https://github.com/jackcvr/sigdis#readme
Project-URL: Issues, https://github.com/jackcvr/sigdis/issues
Project-URL: Source, https://github.com/jackcvr/sigdis
Author-email: Andrii Kuzmin <jack.cvr@gmail.com>
License-Expression: MIT
License-File: LICENSE.txt
Keywords: dispatcher,events,signals
Classifier: Development Status :: 4 - Beta
Classifier: Programming Language :: Python
Classifier: Programming Language :: Python :: 3.7
Classifier: Programming Language :: Python :: 3.8
Classifier: Programming Language :: Python :: 3.9
Classifier: Programming Language :: Python :: 3.10
Classifier: Programming Language :: Python :: 3.11
Classifier: Programming Language :: Python :: Implementation :: CPython
Classifier: Programming Language :: Python :: Implementation :: PyPy
Requires-Python: >=3.7
